typar/__init__.py
typar/example.py
typar/implementation.py
typar/py.typed
typar-0.1.0.dist-info/LICENSE
typar-0.1.0.dist-info/METADATA
typar-0.1.0.dist-info/WHEEL
typar-0.1.0.dist-info/top_level.txt
typar-0.1.0.dist-info/RECORD
