Metadata-Version: 2.1
Name: typar
Version: 0.1.0
Summary: Fully-typed combinatorial parsing library in Python
Author-email: Yuxiang Wei <ywei40@illinois.edu>
Project-URL: Homepage, https://github.com/UniverseFly/typar
Requires-Python: >=3.10
License-File: LICENSE
